.
MANIFEST.in
README.rst
setup.py
/
pythonpy/__init__.py
pythonpy/__main__.py
pythonpy/find_pycompletion.sh
pythonpy/pycompleter.py
pythonpy.egg-info/PKG-INFO
pythonpy.egg-info/SOURCES.txt
pythonpy.egg-info/dependency_links.txt
pythonpy.egg-info/entry_points.txt
pythonpy.egg-info/top_level.txt
pythonpy/completion/__init__.py
pythonpy/completion/pycompletion.sh
test/test_pythonpy.py