Metadata-Version: 1.0
Name: pythonpy
Version: 0.4.9
Summary: python -c, with tab completion and shorthand
Home-page: https://github.com/Russell91/pythonpy
Author: UNKNOWN
Author-email: UNKNOWN
License: MIT
Platform: UNKNOWN
